nbodykit/__init__.py
nbodykit/batch.py
nbodykit/binned_statistic.py
nbodykit/filters.py
nbodykit/hod.py
nbodykit/lab.py
nbodykit/meshtools.py
nbodykit/mockmaker.py
nbodykit/mpirng.py
nbodykit/transform.py
nbodykit/utils.py
nbodykit/version.py
nbodykit/algorithms/__init__.py
nbodykit/algorithms/cgm.py
nbodykit/algorithms/fftcorr.py
nbodykit/algorithms/fftpower.py
nbodykit/algorithms/fftrecon.py
nbodykit/algorithms/fibercollisions.py
nbodykit/algorithms/fof.py
nbodykit/algorithms/kdtree.py
nbodykit/algorithms/threeptcf.py
nbodykit/algorithms/zhist.py
nbodykit/algorithms/convpower/__init__.py
nbodykit/algorithms/convpower/catalog.py
nbodykit/algorithms/convpower/catalogmesh.py
nbodykit/algorithms/convpower/fkp.py
nbodykit/algorithms/convpower/tests/__init__.py
nbodykit/algorithms/convpower/tests/test_catalog.py
nbodykit/algorithms/convpower/tests/test_catalogmesh.py
nbodykit/algorithms/pair_counters/__init__.py
nbodykit/algorithms/pair_counters/base.py
nbodykit/algorithms/pair_counters/domain.py
nbodykit/algorithms/pair_counters/mocksurvey.py
nbodykit/algorithms/pair_counters/simbox.py
nbodykit/algorithms/pair_counters/corrfunc/__init__.py
nbodykit/algorithms/pair_counters/corrfunc/base.py
nbodykit/algorithms/pair_counters/corrfunc/mocks.py
nbodykit/algorithms/pair_counters/corrfunc/theory.py
nbodykit/algorithms/pair_counters/tests/__init__.py
nbodykit/algorithms/pair_counters/tests/test_1d.py
nbodykit/algorithms/pair_counters/tests/test_2d.py
nbodykit/algorithms/pair_counters/tests/test_angular.py
nbodykit/algorithms/pair_counters/tests/test_projected.py
nbodykit/algorithms/paircount_tpcf/__init__.py
nbodykit/algorithms/paircount_tpcf/estimators.py
nbodykit/algorithms/paircount_tpcf/tpcf.py
nbodykit/algorithms/paircount_tpcf/tests/__init__.py
nbodykit/algorithms/paircount_tpcf/tests/test_1d.py
nbodykit/algorithms/paircount_tpcf/tests/test_2d.py
nbodykit/algorithms/paircount_tpcf/tests/test_angular.py
nbodykit/algorithms/paircount_tpcf/tests/test_projected.py
nbodykit-0.3.16.dist-info/licenses/LICENSE
nbodykit-0.3.16.dist-info/METADATA
nbodykit-0.3.16.dist-info/WHEEL
nbodykit-0.3.16.dist-info/top_level.txt
nbodykit-0.3.16.dist-info/RECORD
