Metadata-Version: 2.4
Name: nbodykit
Version: 0.3.16
Summary: Analysis kit for large-scale structure datasets, the massively parallel way
Home-page: http://github.com/bccp/nbodykit
Author: Yu Feng, Nick Hand, et al
Maintainer: Yu Feng
Maintainer-email: rainwoodman@gmail.com
License: GPL3
License-File: LICENSE
Requires-Dist: numpy
Requires-Dist: scipy
Requires-Dist: astropy
Requires-Dist: pyerfa
Requires-Dist: mpi4py
Requires-Dist: six
Requires-Dist: pmesh
Requires-Dist: kdcount
Requires-Dist: mpsort
Requires-Dist: bigfile
Requires-Dist: pandas
Requires-Dist: dask>=0.14.2
Requires-Dist: cachey
Requires-Dist: sympy!=1.6.0,!=1.6.1
Requires-Dist: numexpr
Requires-Dist: Corrfunc
Requires-Dist: mcfit
Requires-Dist: classylss>=0.2
Provides-Extra: extras
Requires-Dist: h5py; extra == "extras"
Requires-Dist: fitsio; extra == "extras"
Provides-Extra: full
Requires-Dist: h5py; extra == "full"
Requires-Dist: fitsio; extra == "full"
Dynamic: author
Dynamic: home-page
Dynamic: license
Dynamic: license-file
Dynamic: maintainer
Dynamic: maintainer-email
Dynamic: provides-extra
Dynamic: requires-dist
Dynamic: summary
